{
    "习近平签署命令发布军队装备保障条例": [
        {
            "time": "2024-11-10 00:07:32.386277+08:00",
            "hot_index": "7915031"
        },
        {
            "time": "2024-11-10 01:02:43.135401+08:00",
            "hot_index": "7977887"
        }
    ],
    "中央点名后 南昌决心“一拆到底”": [
        {
            "time": "2024-11-10 00:07:32.386277+08:00",
            "hot_index": "7992380"
        },
        {
            "time": "2024-11-10 01:02:43.135401+08:00",
            "hot_index": "7936344"
        }
    ],
    "滞留太空的美宇航员瘦成锥子脸": [
        {
            "time": "2024-11-10 00:07:32.386277+08:00",
            "hot_index": "7876221"
        },
        {
            "time": "2024-11-10 01:02:43.135401+08:00",
            "hot_index": "7882029"
        }
    ],
    "多角度透视五周年“成绩单”": [
        {
            "time": "2024-11-10 00:07:32.386277+08:00",
            "hot_index": "7726823"
        },
        {
            "time": "2024-11-10 01:02:43.135401+08:00",
            "hot_index": "7756677"
        }
    ],
    "郑钦文vs高芙 冲击冠军": [
        {
            "time": "2024-11-10 00:07:32.386277+08:00",
            "hot_index": "7626052"
        },
        {
            "time": "2024-11-10 01:02:43.135401+08:00",
            "hot_index": "7664576"
        }
    ],
    "药店晕倒无人扶老人已去世": [
        {
            "time": "2024-11-10 00:07:32.386277+08:00",
            "hot_index": "7581891"
        },
        {
            "time": "2024-11-10 01:02:43.135401+08:00",
            "hot_index": "6492029"
        }
    ],
    "女友收50万彩礼后出轨前男友": [
        {
            "time": "2024-11-10 00:07:32.386277+08:00",
            "hot_index": "7478703"
        },
        {
            "time": "2024-11-10 01:02:43.135401+08:00",
            "hot_index": "7502859"
        }
    ],
    "贵州10岁女孩展示轻功": [
        {
            "time": "2024-11-10 00:07:32.386277+08:00",
            "hot_index": "7373944"
        },
        {
            "time": "2024-11-10 01:02:43.135401+08:00",
            "hot_index": "7081157"
        }
    ],
    "郑钦文解锁所有级别赛事决赛": [
        {
            "time": "2024-11-10 00:07:32.386277+08:00",
            "hot_index": "7224795"
        },
        {
            "time": "2024-11-10 01:02:43.135401+08:00",
            "hot_index": "7248677"
        }
    ],
    "男子养了3年的小狗竟是野狼": [
        {
            "time": "2024-11-10 00:07:32.386277+08:00",
            "hot_index": "7191198"
        },
        {
            "time": "2024-11-10 01:02:43.135401+08:00",
            "hot_index": "6211640"
        }
    ],
    "自带饭勺的小鸟又来过冬啦": [
        {
            "time": "2024-11-10 00:07:32.386277+08:00",
            "hot_index": "7058970"
        },
        {
            "time": "2024-11-10 01:02:43.135401+08:00",
            "hot_index": "6712009"
        }
    ],
    "吴磊意外受伤 工作室紧急致歉": [
        {
            "time": "2024-11-10 00:07:32.386277+08:00",
            "hot_index": "6937275"
        }
    ],
    "中医对急症束手无策？误解！": [
        {
            "time": "2024-11-10 00:07:32.386277+08:00",
            "hot_index": "6898761"
        },
        {
            "time": "2024-11-10 01:02:43.135401+08:00",
            "hot_index": "6820629"
        }
    ],
    "美43只雌猴逃出实验室 或带致命病毒": [
        {
            "time": "2024-11-10 00:07:32.386277+08:00",
            "hot_index": "6754325"
        },
        {
            "time": "2024-11-10 01:02:43.135401+08:00",
            "hot_index": "7113471"
        }
    ],
    "建议每个恐华症的人都到中国看看": [
        {
            "time": "2024-11-10 00:07:32.386277+08:00",
            "hot_index": "6687497"
        },
        {
            "time": "2024-11-10 01:02:43.135401+08:00",
            "hot_index": "6344829"
        }
    ],
    "马斯克开刷政治存在感": [
        {
            "time": "2024-11-10 00:07:32.386277+08:00",
            "hot_index": "6538881"
        },
        {
            "time": "2024-11-10 01:02:43.135401+08:00",
            "hot_index": "6533143"
        }
    ],
    "上海一彩民中奖1003万元": [
        {
            "time": "2024-11-10 00:07:32.386277+08:00",
            "hot_index": "6466711"
        },
        {
            "time": "2024-11-10 01:02:43.135401+08:00",
            "hot_index": "6935821"
        }
    ],
    "丁禹兮演出了书里的微表情": [
        {
            "time": "2024-11-10 00:07:32.386277+08:00",
            "hot_index": "6364339"
        }
    ],
    "欧盟考虑用美气取代俄气": [
        {
            "time": "2024-11-10 00:07:32.386277+08:00",
            "hot_index": "6236312"
        }
    ],
    "60岁自驾游阿姨仍在出走": [
        {
            "time": "2024-11-10 00:07:32.386277+08:00",
            "hot_index": "6148075"
        },
        {
            "time": "2024-11-10 01:02:43.135401+08:00",
            "hot_index": "5857510"
        }
    ],
    "大额存单进入“1”时代": [
        {
            "time": "2024-11-10 00:07:32.386277+08:00",
            "hot_index": "6098274"
        },
        {
            "time": "2024-11-10 01:02:43.135401+08:00",
            "hot_index": "4692985"
        }
    ],
    "3名95后女干部学历为大专？当地回应": [
        {
            "time": "2024-11-10 00:07:32.386277+08:00",
            "hot_index": "5946531"
        },
        {
            "time": "2024-11-10 01:02:43.135401+08:00",
            "hot_index": "5987423"
        }
    ],
    "张婉婷觉得麦琳确实是有问题": [
        {
            "time": "2024-11-10 00:07:32.386277+08:00",
            "hot_index": "5837543"
        }
    ],
    "劳斯莱斯女车主丈夫坦言拒赔原因": [
        {
            "time": "2024-11-10 00:07:32.386277+08:00",
            "hot_index": "5753995"
        },
        {
            "time": "2024-11-10 01:02:43.135401+08:00",
            "hot_index": "5762722"
        }
    ],
    "美国演员托尼托德去世": [
        {
            "time": "2024-11-10 00:07:32.386277+08:00",
            "hot_index": "5617788"
        },
        {
            "time": "2024-11-10 01:02:43.135401+08:00",
            "hot_index": "5592894"
        }
    ],
    "骑行学生：刚开始好玩 堵在路上受罪": [
        {
            "time": "2024-11-10 00:07:32.386277+08:00",
            "hot_index": "5550918"
        },
        {
            "time": "2024-11-10 01:02:43.135401+08:00",
            "hot_index": "6671496"
        }
    ],
    "市民散步顺手救了一只“鸟界二哈”": [
        {
            "time": "2024-11-10 00:07:32.386277+08:00",
            "hot_index": "5451662"
        },
        {
            "time": "2024-11-10 01:02:43.135401+08:00",
            "hot_index": "5423043"
        }
    ],
    "一觉醒来郑钦文成了亚洲一姐": [
        {
            "time": "2024-11-10 00:07:32.386277+08:00",
            "hot_index": "5364230"
        }
    ],
    "月销破万辆 新能源“国家队”崛起？": [
        {
            "time": "2024-11-10 00:07:32.386277+08:00",
            "hot_index": "5272559"
        },
        {
            "time": "2024-11-10 01:02:43.135401+08:00",
            "hot_index": "5311222"
        }
    ],
    "刀郎澳门演唱会《冲动的惩罚》好炸裂": [
        {
            "time": "2024-11-10 00:07:32.386277+08:00",
            "hot_index": "5142864"
        },
        {
            "time": "2024-11-10 01:02:43.135401+08:00",
            "hot_index": "3243521"
        }
    ],
    "知情人称要求陪睡公司总有女生应聘": [
        {
            "time": "2024-11-10 00:07:32.386277+08:00",
            "hot_index": "5083028"
        },
        {
            "time": "2024-11-10 01:02:43.135401+08:00",
            "hot_index": "5207939"
        }
    ],
    "特朗普已准备再次退出巴黎协定": [
        {
            "time": "2024-11-10 00:07:32.386277+08:00",
            "hot_index": "4925389"
        },
        {
            "time": "2024-11-10 01:02:43.135401+08:00",
            "hot_index": "4566614"
        }
    ],
    "张泉灵说倪萍姐姐该你了": [
        {
            "time": "2024-11-10 00:07:32.386277+08:00",
            "hot_index": "4806848"
        },
        {
            "time": "2024-11-10 01:02:43.135401+08:00",
            "hot_index": "3814176"
        }
    ],
    "济南小伙每周走读去韩国读博": [
        {
            "time": "2024-11-10 00:07:32.386277+08:00",
            "hot_index": "4737876"
        }
    ],
    "任由电梯“带病”载人 提示难言温馨": [
        {
            "time": "2024-11-10 00:07:32.386277+08:00",
            "hot_index": "4605776"
        }
    ],
    "警方通报农田水沟内现无名女尸": [
        {
            "time": "2024-11-10 00:07:32.386277+08:00",
            "hot_index": "4579470"
        },
        {
            "time": "2024-11-10 01:02:43.135401+08:00",
            "hot_index": "5097726"
        }
    ],
    "妇幼保健院更衣室藏摄像头": [
        {
            "time": "2024-11-10 00:07:32.386277+08:00",
            "hot_index": "4448750"
        },
        {
            "time": "2024-11-10 01:02:43.135401+08:00",
            "hot_index": "4032062"
        }
    ],
    "医院偶遇丁禹兮看病": [
        {
            "time": "2024-11-10 00:07:32.386277+08:00",
            "hot_index": "4332600"
        }
    ],
    "郑州共享单车超区骑行将强制锁车": [
        {
            "time": "2024-11-10 00:07:32.386277+08:00",
            "hot_index": "4236058"
        },
        {
            "time": "2024-11-10 01:02:43.135401+08:00",
            "hot_index": "4212148"
        }
    ],
    "排面！郑钦文再上新闻联播": [
        {
            "time": "2024-11-10 00:07:32.386277+08:00",
            "hot_index": "4107742"
        },
        {
            "time": "2024-11-10 01:02:43.135401+08:00",
            "hot_index": "3100000"
        }
    ],
    "商家回应女子疑似河豚中毒": [
        {
            "time": "2024-11-10 00:07:32.386277+08:00",
            "hot_index": "4055654"
        }
    ],
    "百万粉丝博主江边捡垃圾发现散落人骨": [
        {
            "time": "2024-11-10 00:07:32.386277+08:00",
            "hot_index": "3993230"
        },
        {
            "time": "2024-11-10 01:02:43.135401+08:00",
            "hot_index": "4834639"
        }
    ],
    "新加坡总理回应李显龙家族内斗": [
        {
            "time": "2024-11-10 00:07:32.386277+08:00",
            "hot_index": "3811094"
        },
        {
            "time": "2024-11-10 01:02:43.135401+08:00",
            "hot_index": "4420116"
        }
    ],
    "刀郎《川江号子》响彻澳门": [
        {
            "time": "2024-11-10 00:07:32.386277+08:00",
            "hot_index": "3738874"
        },
        {
            "time": "2024-11-10 01:02:43.135401+08:00",
            "hot_index": "3682646"
        }
    ],
    "麦琳退了女儿喜欢的汉服": [
        {
            "time": "2024-11-10 00:07:32.386277+08:00",
            "hot_index": "3643090"
        },
        {
            "time": "2024-11-10 01:02:43.135401+08:00",
            "hot_index": "3790451"
        }
    ],
    "机器狼群出来爬坡“遛弯”了": [
        {
            "time": "2024-11-10 00:07:32.386277+08:00",
            "hot_index": "3520453"
        },
        {
            "time": "2024-11-10 01:02:43.135401+08:00",
            "hot_index": "3485804"
        }
    ],
    "美媒:马斯克参与特朗普泽连斯基通话": [
        {
            "time": "2024-11-10 00:07:32.386277+08:00",
            "hot_index": "3490296"
        }
    ],
    "郑钦文总决赛已狂揽1600万奖金": [
        {
            "time": "2024-11-10 00:07:32.386277+08:00",
            "hot_index": "3361004"
        },
        {
            "time": "2024-11-10 01:02:43.135401+08:00",
            "hot_index": "4166725"
        }
    ],
    "代炒菜业务走红江浙沪": [
        {
            "time": "2024-11-10 00:07:32.386277+08:00",
            "hot_index": "3293495"
        },
        {
            "time": "2024-11-10 01:02:43.135401+08:00",
            "hot_index": "3177201"
        }
    ],
    "李清照为护文物不惜入狱手撕渣男": [
        {
            "time": "2024-11-10 00:07:32.386277+08:00",
            "hot_index": "3194336"
        }
    ],
    "妙妙 你怕我": [
        {
            "time": "2024-11-10 00:07:32.386277+08:00",
            "hot_index": "3100000"
        }
    ],
    "刀郎歌迷定制99.99米横幅万人签名": [
        {
            "time": "2024-11-10 01:02:43.135401+08:00",
            "hot_index": "7492970"
        }
    ],
    "女子6次敲诈海底捞被判7个月": [
        {
            "time": "2024-11-10 01:02:43.135401+08:00",
            "hot_index": "7377798"
        }
    ],
    "麦琳 熏鸡事件": [
        {
            "time": "2024-11-10 01:02:43.135401+08:00",
            "hot_index": "6179290"
        }
    ],
    "徐子尧在刀郎演唱会上飙高音": [
        {
            "time": "2024-11-10 01:02:43.135401+08:00",
            "hot_index": "6059445"
        }
    ],
    "妈妈要求爱豆女儿退圈照顾弟弟": [
        {
            "time": "2024-11-10 01:02:43.135401+08:00",
            "hot_index": "5629385"
        }
    ],
    "济南回应爆米花卖260元：市场调节价": [
        {
            "time": "2024-11-10 01:02:43.135401+08:00",
            "hot_index": "5130467"
        }
    ],
    "德云社唯一女弟子斗笑社路透": [
        {
            "time": "2024-11-10 01:02:43.135401+08:00",
            "hot_index": "4922757"
        }
    ],
    "中国房地产报：楼市初步止跌": [
        {
            "time": "2024-11-10 01:02:43.135401+08:00",
            "hot_index": "4717877"
        }
    ],
    "这次特朗普能治好“美国病”吗": [
        {
            "time": "2024-11-10 01:02:43.135401+08:00",
            "hot_index": "4366183"
        }
    ],
    "黄圣依没有杨子描述的痣": [
        {
            "time": "2024-11-10 01:02:43.135401+08:00",
            "hot_index": "3989007"
        }
    ],
    "苏57再炫技：飞行员10年前来过珠海": [
        {
            "time": "2024-11-10 01:02:43.135401+08:00",
            "hot_index": "3574411"
        }
    ],
    "桂林火车站通报员工上班盘核桃": [
        {
            "time": "2024-11-10 01:02:43.135401+08:00",
            "hot_index": "3392046"
        }
    ]
}