{
    "神十四成功对接空间站": [
        {
            "time": "2022-06-06 00:05:45.407270+08:00",
            "hot_index": "4959450"
        },
        {
            "time": "2022-06-06 01:03:07.382417+08:00",
            "hot_index": "4914834"
        },
        {
            "time": "2022-06-06 02:06:48.552259+08:00",
            "hot_index": "4943877"
        },
        {
            "time": "2022-06-06 03:01:51.128454+08:00",
            "hot_index": "4939652"
        },
        {
            "time": "2022-06-06 04:02:36.746071+08:00",
            "hot_index": "4932411"
        },
        {
            "time": "2022-06-06 05:04:11.365831+08:00",
            "hot_index": "4942157"
        },
        {
            "time": "2022-06-06 06:02:10.705190+08:00",
            "hot_index": "4916962"
        },
        {
            "time": "2022-06-06 07:02:22.039998+08:00",
            "hot_index": "4973475"
        },
        {
            "time": "2022-06-06 08:26:34.882912+08:00",
            "hot_index": "4944610"
        }
    ],
    "国企书记夫人用宾利堵车位？官方回应": [
        {
            "time": "2022-06-06 00:05:45.407270+08:00",
            "hot_index": "4911833"
        },
        {
            "time": "2022-06-06 01:03:07.382417+08:00",
            "hot_index": "4446439"
        }
    ],
    "上海辟谣6月20日再封1个月": [
        {
            "time": "2022-06-06 00:05:45.407270+08:00",
            "hot_index": "4896778"
        },
        {
            "time": "2022-06-06 01:03:07.382417+08:00",
            "hot_index": "4965634"
        },
        {
            "time": "2022-06-06 02:06:48.552259+08:00",
            "hot_index": "4996306"
        },
        {
            "time": "2022-06-06 03:01:51.128454+08:00",
            "hot_index": "4968953"
        },
        {
            "time": "2022-06-06 04:02:36.746071+08:00",
            "hot_index": "4951146"
        },
        {
            "time": "2022-06-06 05:04:11.365831+08:00",
            "hot_index": "4958976"
        },
        {
            "time": "2022-06-06 06:02:10.705190+08:00",
            "hot_index": "4959914"
        },
        {
            "time": "2022-06-06 07:02:22.039998+08:00",
            "hot_index": "4951304"
        },
        {
            "time": "2022-06-06 08:26:34.882912+08:00",
            "hot_index": "2227271"
        }
    ],
    "神十四乘组进驻天和核心舱": [
        {
            "time": "2022-06-06 00:05:45.407270+08:00",
            "hot_index": "4706823"
        },
        {
            "time": "2022-06-06 01:03:07.382417+08:00",
            "hot_index": "4793829"
        },
        {
            "time": "2022-06-06 02:06:48.552259+08:00",
            "hot_index": "4723251"
        },
        {
            "time": "2022-06-06 03:01:51.128454+08:00",
            "hot_index": "4784087"
        },
        {
            "time": "2022-06-06 04:02:36.746071+08:00",
            "hot_index": "4752610"
        },
        {
            "time": "2022-06-06 05:04:11.365831+08:00",
            "hot_index": "4707212"
        },
        {
            "time": "2022-06-06 06:02:10.705190+08:00",
            "hot_index": "4749254"
        },
        {
            "time": "2022-06-06 07:02:22.039998+08:00",
            "hot_index": "4717006"
        },
        {
            "time": "2022-06-06 08:26:34.882912+08:00",
            "hot_index": "4714096"
        }
    ],
    "中国女排不敌泰国队": [
        {
            "time": "2022-06-06 00:05:45.407270+08:00",
            "hot_index": "4648851"
        },
        {
            "time": "2022-06-06 01:03:07.382417+08:00",
            "hot_index": "4621795"
        },
        {
            "time": "2022-06-06 02:06:48.552259+08:00",
            "hot_index": "4403341"
        },
        {
            "time": "2022-06-06 03:01:51.128454+08:00",
            "hot_index": "4462850"
        },
        {
            "time": "2022-06-06 04:02:36.746071+08:00",
            "hot_index": "4430837"
        },
        {
            "time": "2022-06-06 05:04:11.365831+08:00",
            "hot_index": "4582803"
        },
        {
            "time": "2022-06-06 06:02:10.705190+08:00",
            "hot_index": "4513074"
        },
        {
            "time": "2022-06-06 07:02:22.039998+08:00",
            "hot_index": "4549880"
        },
        {
            "time": "2022-06-06 08:26:34.882912+08:00",
            "hot_index": "3606429"
        }
    ],
    "美国12岁儿童持枪抢劫加油站": [
        {
            "time": "2022-06-06 00:05:45.407270+08:00",
            "hot_index": "4550558"
        },
        {
            "time": "2022-06-06 01:03:07.382417+08:00",
            "hot_index": "3693453"
        },
        {
            "time": "2022-06-06 02:06:48.552259+08:00",
            "hot_index": "3238303"
        },
        {
            "time": "2022-06-06 03:01:51.128454+08:00",
            "hot_index": "4384798"
        },
        {
            "time": "2022-06-06 04:02:36.746071+08:00",
            "hot_index": "4076827"
        },
        {
            "time": "2022-06-06 05:04:11.365831+08:00",
            "hot_index": "3686894"
        },
        {
            "time": "2022-06-06 06:02:10.705190+08:00",
            "hot_index": "3629633"
        },
        {
            "time": "2022-06-06 07:02:22.039998+08:00",
            "hot_index": "3887687"
        },
        {
            "time": "2022-06-06 08:26:34.882912+08:00",
            "hot_index": "3266998"
        }
    ],
    "2岁男童眼睛现4条寄生虫游动": [
        {
            "time": "2022-06-06 00:05:45.407270+08:00",
            "hot_index": "4402897"
        },
        {
            "time": "2022-06-06 01:03:07.382417+08:00",
            "hot_index": "4048257"
        },
        {
            "time": "2022-06-06 02:06:48.552259+08:00",
            "hot_index": "4323692"
        },
        {
            "time": "2022-06-06 03:01:51.128454+08:00",
            "hot_index": "4542723"
        },
        {
            "time": "2022-06-06 04:02:36.746071+08:00",
            "hot_index": "4557261"
        },
        {
            "time": "2022-06-06 05:04:11.365831+08:00",
            "hot_index": "4431733"
        },
        {
            "time": "2022-06-06 06:02:10.705190+08:00",
            "hot_index": "4496980"
        },
        {
            "time": "2022-06-06 07:02:22.039998+08:00",
            "hot_index": "4488629"
        },
        {
            "time": "2022-06-06 08:26:34.882912+08:00",
            "hot_index": "3904115"
        }
    ],
    "河南大学脑出血去世女生堂姐发声": [
        {
            "time": "2022-06-06 00:05:45.407270+08:00",
            "hot_index": "4318033"
        },
        {
            "time": "2022-06-06 01:03:07.382417+08:00",
            "hot_index": "3987775"
        },
        {
            "time": "2022-06-06 02:06:48.552259+08:00",
            "hot_index": "3937345"
        },
        {
            "time": "2022-06-06 03:01:51.128454+08:00",
            "hot_index": "4221816"
        },
        {
            "time": "2022-06-06 04:02:36.746071+08:00",
            "hot_index": "4306311"
        },
        {
            "time": "2022-06-06 05:04:11.365831+08:00",
            "hot_index": "4358808"
        },
        {
            "time": "2022-06-06 06:02:10.705190+08:00",
            "hot_index": "4305706"
        },
        {
            "time": "2022-06-06 07:02:22.039998+08:00",
            "hot_index": "4355146"
        },
        {
            "time": "2022-06-06 08:26:34.882912+08:00",
            "hot_index": "4401842"
        }
    ],
    "中国邮政押运高考试卷 警车护航": [
        {
            "time": "2022-06-06 00:05:45.407270+08:00",
            "hot_index": "4270177"
        },
        {
            "time": "2022-06-06 01:03:07.382417+08:00",
            "hot_index": "4887238"
        },
        {
            "time": "2022-06-06 02:06:48.552259+08:00",
            "hot_index": "4896356"
        },
        {
            "time": "2022-06-06 03:01:51.128454+08:00",
            "hot_index": "4813914"
        },
        {
            "time": "2022-06-06 04:02:36.746071+08:00",
            "hot_index": "4860518"
        },
        {
            "time": "2022-06-06 05:04:11.365831+08:00",
            "hot_index": "4811998"
        },
        {
            "time": "2022-06-06 06:02:10.705190+08:00",
            "hot_index": "4878100"
        },
        {
            "time": "2022-06-06 07:02:22.039998+08:00",
            "hot_index": "4856880"
        },
        {
            "time": "2022-06-06 08:26:34.882912+08:00",
            "hot_index": "3070741"
        }
    ],
    "买黄金的年轻人们 支棱不起来了？": [
        {
            "time": "2022-06-06 00:05:45.407270+08:00",
            "hot_index": "4124226"
        },
        {
            "time": "2022-06-06 01:03:07.382417+08:00",
            "hot_index": "3812989"
        },
        {
            "time": "2022-06-06 02:06:48.552259+08:00",
            "hot_index": "4218843"
        },
        {
            "time": "2022-06-06 03:01:51.128454+08:00",
            "hot_index": "4186787"
        },
        {
            "time": "2022-06-06 04:02:36.746071+08:00",
            "hot_index": "4123512"
        },
        {
            "time": "2022-06-06 05:04:11.365831+08:00",
            "hot_index": "4182604"
        },
        {
            "time": "2022-06-06 06:02:10.705190+08:00",
            "hot_index": "4063118"
        },
        {
            "time": "2022-06-06 07:02:22.039998+08:00",
            "hot_index": "4161114"
        },
        {
            "time": "2022-06-06 08:26:34.882912+08:00",
            "hot_index": "3722833"
        }
    ],
    "D2809列车进站前监控曝光": [
        {
            "time": "2022-06-06 00:05:45.407270+08:00",
            "hot_index": "4026099"
        },
        {
            "time": "2022-06-06 01:03:07.382417+08:00",
            "hot_index": "2008847"
        },
        {
            "time": "2022-06-06 02:06:48.552259+08:00",
            "hot_index": "2742107"
        },
        {
            "time": "2022-06-06 03:01:51.128454+08:00",
            "hot_index": "2637896"
        },
        {
            "time": "2022-06-06 04:02:36.746071+08:00",
            "hot_index": "2730046"
        },
        {
            "time": "2022-06-06 05:04:11.365831+08:00",
            "hot_index": "2550445"
        },
        {
            "time": "2022-06-06 06:02:10.705190+08:00",
            "hot_index": "2370214"
        },
        {
            "time": "2022-06-06 07:02:22.039998+08:00",
            "hot_index": "2672229"
        },
        {
            "time": "2022-06-06 08:26:34.882912+08:00",
            "hot_index": "2782554"
        }
    ],
    "《一路向前》剧组2人落水溺亡": [
        {
            "time": "2022-06-06 00:05:45.407270+08:00",
            "hot_index": "3944606"
        },
        {
            "time": "2022-06-06 01:03:07.382417+08:00",
            "hot_index": "4300523"
        },
        {
            "time": "2022-06-06 02:06:48.552259+08:00",
            "hot_index": "4663726"
        },
        {
            "time": "2022-06-06 03:01:51.128454+08:00",
            "hot_index": "4664387"
        },
        {
            "time": "2022-06-06 04:02:36.746071+08:00",
            "hot_index": "4652896"
        },
        {
            "time": "2022-06-06 05:04:11.365831+08:00",
            "hot_index": "4659409"
        },
        {
            "time": "2022-06-06 06:02:10.705190+08:00",
            "hot_index": "4670093"
        },
        {
            "time": "2022-06-06 07:02:22.039998+08:00",
            "hot_index": "4608466"
        },
        {
            "time": "2022-06-06 08:26:34.882912+08:00",
            "hot_index": "4182560"
        }
    ],
    "女子称开50辆宾利堵截被占车位": [
        {
            "time": "2022-06-06 00:05:45.407270+08:00",
            "hot_index": "3871755"
        }
    ],
    "只因朋友没赶上车七旬老人4夺方向盘": [
        {
            "time": "2022-06-06 00:05:45.407270+08:00",
            "hot_index": "3767763"
        },
        {
            "time": "2022-06-06 01:03:07.382417+08:00",
            "hot_index": "3031051"
        },
        {
            "time": "2022-06-06 02:06:48.552259+08:00",
            "hot_index": "4565833"
        },
        {
            "time": "2022-06-06 03:01:51.128454+08:00",
            "hot_index": "4050871"
        },
        {
            "time": "2022-06-06 04:02:36.746071+08:00",
            "hot_index": "3789913"
        },
        {
            "time": "2022-06-06 05:04:11.365831+08:00",
            "hot_index": "3784966"
        },
        {
            "time": "2022-06-06 06:02:10.705190+08:00",
            "hot_index": "4243525"
        },
        {
            "time": "2022-06-06 07:02:22.039998+08:00",
            "hot_index": "4056113"
        },
        {
            "time": "2022-06-06 08:26:34.882912+08:00",
            "hot_index": "4389985"
        }
    ],
    "“核酸小屋”不便民？网友吵翻了": [
        {
            "time": "2022-06-06 00:05:45.407270+08:00",
            "hot_index": "3616129"
        },
        {
            "time": "2022-06-06 01:03:07.382417+08:00",
            "hot_index": "2861803"
        },
        {
            "time": "2022-06-06 02:06:48.552259+08:00",
            "hot_index": "3401951"
        },
        {
            "time": "2022-06-06 03:01:51.128454+08:00",
            "hot_index": "3234222"
        },
        {
            "time": "2022-06-06 04:02:36.746071+08:00",
            "hot_index": "3978897"
        },
        {
            "time": "2022-06-06 05:04:11.365831+08:00",
            "hot_index": "3318451"
        },
        {
            "time": "2022-06-06 06:02:10.705190+08:00",
            "hot_index": "3215919"
        },
        {
            "time": "2022-06-06 07:02:22.039998+08:00",
            "hot_index": "3234141"
        },
        {
            "time": "2022-06-06 08:26:34.882912+08:00",
            "hot_index": "2171054"
        }
    ],
    "动画还原D2809次列车脱线事故": [
        {
            "time": "2022-06-06 00:05:45.407270+08:00",
            "hot_index": "3506322"
        },
        {
            "time": "2022-06-06 01:03:07.382417+08:00",
            "hot_index": "3327912"
        },
        {
            "time": "2022-06-06 02:06:48.552259+08:00",
            "hot_index": "3642336"
        },
        {
            "time": "2022-06-06 03:01:51.128454+08:00",
            "hot_index": "3642934"
        },
        {
            "time": "2022-06-06 04:02:36.746071+08:00",
            "hot_index": "3020796"
        },
        {
            "time": "2022-06-06 05:04:11.365831+08:00",
            "hot_index": "3411107"
        },
        {
            "time": "2022-06-06 06:02:10.705190+08:00",
            "hot_index": "2899038"
        },
        {
            "time": "2022-06-06 07:02:22.039998+08:00",
            "hot_index": "3007899"
        }
    ],
    "是谁在缔造越南经济神话？": [
        {
            "time": "2022-06-06 00:05:45.407270+08:00",
            "hot_index": "3443903"
        },
        {
            "time": "2022-06-06 01:03:07.382417+08:00",
            "hot_index": "4195806"
        },
        {
            "time": "2022-06-06 02:06:48.552259+08:00",
            "hot_index": "3052341"
        },
        {
            "time": "2022-06-06 03:01:51.128454+08:00",
            "hot_index": "3103067"
        },
        {
            "time": "2022-06-06 04:02:36.746071+08:00",
            "hot_index": "3666086"
        },
        {
            "time": "2022-06-06 05:04:11.365831+08:00",
            "hot_index": "4289831"
        },
        {
            "time": "2022-06-06 06:02:10.705190+08:00",
            "hot_index": "3887701"
        },
        {
            "time": "2022-06-06 07:02:22.039998+08:00",
            "hot_index": "3433046"
        },
        {
            "time": "2022-06-06 08:26:34.882912+08:00",
            "hot_index": "2653975"
        }
    ],
    "那些被嫌弃的新冠康复者": [
        {
            "time": "2022-06-06 00:05:45.407270+08:00",
            "hot_index": "3387444"
        },
        {
            "time": "2022-06-06 01:03:07.382417+08:00",
            "hot_index": "3739589"
        },
        {
            "time": "2022-06-06 02:06:48.552259+08:00",
            "hot_index": "4155697"
        },
        {
            "time": "2022-06-06 03:01:51.128454+08:00",
            "hot_index": "3841837"
        },
        {
            "time": "2022-06-06 04:02:36.746071+08:00",
            "hot_index": "3288212"
        },
        {
            "time": "2022-06-06 05:04:11.365831+08:00",
            "hot_index": "3978589"
        },
        {
            "time": "2022-06-06 06:02:10.705190+08:00",
            "hot_index": "4109754"
        },
        {
            "time": "2022-06-06 07:02:22.039998+08:00",
            "hot_index": "3957779"
        },
        {
            "time": "2022-06-06 08:26:34.882912+08:00",
            "hot_index": "3404188"
        }
    ],
    "最高2000多元 上门核酸检测靠谱吗？": [
        {
            "time": "2022-06-06 00:05:45.407270+08:00",
            "hot_index": "3261257"
        },
        {
            "time": "2022-06-06 05:04:11.365831+08:00",
            "hot_index": "2117150"
        }
    ],
    "中国女排排名升至世界第二": [
        {
            "time": "2022-06-06 00:05:45.407270+08:00",
            "hot_index": "3160441"
        },
        {
            "time": "2022-06-06 01:03:07.382417+08:00",
            "hot_index": "2220688"
        },
        {
            "time": "2022-06-06 02:06:48.552259+08:00",
            "hot_index": "2452253"
        },
        {
            "time": "2022-06-06 03:01:51.128454+08:00",
            "hot_index": "2408208"
        },
        {
            "time": "2022-06-06 04:02:36.746071+08:00",
            "hot_index": "3342199"
        },
        {
            "time": "2022-06-06 05:04:11.365831+08:00",
            "hot_index": "2376143"
        },
        {
            "time": "2022-06-06 06:02:10.705190+08:00",
            "hot_index": "2549930"
        },
        {
            "time": "2022-06-06 07:02:22.039998+08:00",
            "hot_index": "2703690"
        }
    ],
    "西南交大发文悼念D2809殉职司机": [
        {
            "time": "2022-06-06 00:05:45.407270+08:00",
            "hot_index": "3048307"
        },
        {
            "time": "2022-06-06 01:03:07.382417+08:00",
            "hot_index": "2385293"
        },
        {
            "time": "2022-06-06 02:06:48.552259+08:00",
            "hot_index": "2567401"
        },
        {
            "time": "2022-06-06 03:01:51.128454+08:00",
            "hot_index": "2585737"
        },
        {
            "time": "2022-06-06 04:02:36.746071+08:00",
            "hot_index": "2612305"
        },
        {
            "time": "2022-06-06 05:04:11.365831+08:00",
            "hot_index": "3083809"
        },
        {
            "time": "2022-06-06 06:02:10.705190+08:00",
            "hot_index": "2710803"
        },
        {
            "time": "2022-06-06 07:02:22.039998+08:00",
            "hot_index": "2808882"
        },
        {
            "time": "2022-06-06 08:26:34.882912+08:00",
            "hot_index": "2371456"
        }
    ],
    "核酸采样亭数万一个 谁在挖商机？": [
        {
            "time": "2022-06-06 00:05:45.407270+08:00",
            "hot_index": "2929532"
        },
        {
            "time": "2022-06-06 01:03:07.382417+08:00",
            "hot_index": "2947055"
        },
        {
            "time": "2022-06-06 02:06:48.552259+08:00",
            "hot_index": "2919670"
        },
        {
            "time": "2022-06-06 03:01:51.128454+08:00",
            "hot_index": "2933208"
        },
        {
            "time": "2022-06-06 04:02:36.746071+08:00",
            "hot_index": "2900525"
        },
        {
            "time": "2022-06-06 05:04:11.365831+08:00",
            "hot_index": "2999316"
        },
        {
            "time": "2022-06-06 06:02:10.705190+08:00",
            "hot_index": "2982667"
        },
        {
            "time": "2022-06-06 07:02:22.039998+08:00",
            "hot_index": "2936690"
        },
        {
            "time": "2022-06-06 08:26:34.882912+08:00",
            "hot_index": "2986726"
        }
    ],
    "俄罗斯第三阶段军事目标 信息量很大": [
        {
            "time": "2022-06-06 00:05:45.407270+08:00",
            "hot_index": "2890589"
        },
        {
            "time": "2022-06-06 01:03:07.382417+08:00",
            "hot_index": "2548780"
        },
        {
            "time": "2022-06-06 02:06:48.552259+08:00",
            "hot_index": "3764603"
        },
        {
            "time": "2022-06-06 03:01:51.128454+08:00",
            "hot_index": "3707637"
        },
        {
            "time": "2022-06-06 04:02:36.746071+08:00",
            "hot_index": "2331623"
        },
        {
            "time": "2022-06-06 05:04:11.365831+08:00",
            "hot_index": "3837672"
        },
        {
            "time": "2022-06-06 06:02:10.705190+08:00",
            "hot_index": "3464215"
        },
        {
            "time": "2022-06-06 07:02:22.039998+08:00",
            "hot_index": "3641639"
        }
    ],
    "列车司机谈D2809“5秒制动”": [
        {
            "time": "2022-06-06 00:05:45.407270+08:00",
            "hot_index": "2785135"
        },
        {
            "time": "2022-06-06 05:04:11.365831+08:00",
            "hot_index": "4045258"
        },
        {
            "time": "2022-06-06 08:26:34.882912+08:00",
            "hot_index": "3821823"
        }
    ],
    "上海3地列为中风险地区": [
        {
            "time": "2022-06-06 00:05:45.407270+08:00",
            "hot_index": "2666166"
        },
        {
            "time": "2022-06-06 01:03:07.382417+08:00",
            "hot_index": "3159948"
        },
        {
            "time": "2022-06-06 02:06:48.552259+08:00",
            "hot_index": "2836589"
        },
        {
            "time": "2022-06-06 03:01:51.128454+08:00",
            "hot_index": "3392127"
        },
        {
            "time": "2022-06-06 04:02:36.746071+08:00",
            "hot_index": "4274857"
        },
        {
            "time": "2022-06-06 05:04:11.365831+08:00",
            "hot_index": "3233167"
        },
        {
            "time": "2022-06-06 06:02:10.705190+08:00",
            "hot_index": "3390785"
        },
        {
            "time": "2022-06-06 07:02:22.039998+08:00",
            "hot_index": "3388613"
        }
    ],
    "航天员妈妈流泪隔空向女儿挥手": [
        {
            "time": "2022-06-06 00:05:45.407270+08:00",
            "hot_index": "2523298"
        },
        {
            "time": "2022-06-06 01:03:07.382417+08:00",
            "hot_index": "2181235"
        },
        {
            "time": "2022-06-06 02:06:48.552259+08:00",
            "hot_index": "3388411"
        },
        {
            "time": "2022-06-06 03:01:51.128454+08:00",
            "hot_index": "3943727"
        },
        {
            "time": "2022-06-06 04:02:36.746071+08:00",
            "hot_index": "3140891"
        },
        {
            "time": "2022-06-06 05:04:11.365831+08:00",
            "hot_index": "2743240"
        },
        {
            "time": "2022-06-06 06:02:10.705190+08:00",
            "hot_index": "3100370"
        },
        {
            "time": "2022-06-06 07:02:22.039998+08:00",
            "hot_index": "4208502"
        },
        {
            "time": "2022-06-06 08:26:34.882912+08:00",
            "hot_index": "3186836"
        }
    ],
    "私人飞机误闯拜登别墅限制空域": [
        {
            "time": "2022-06-06 00:05:45.407270+08:00",
            "hot_index": "2406839"
        },
        {
            "time": "2022-06-06 01:03:07.382417+08:00",
            "hot_index": "2644653"
        },
        {
            "time": "2022-06-06 03:01:51.128454+08:00",
            "hot_index": "2222261"
        }
    ],
    "金莎新冠治愈出院": [
        {
            "time": "2022-06-06 00:05:45.407270+08:00",
            "hot_index": "2300672"
        },
        {
            "time": "2022-06-06 01:03:07.382417+08:00",
            "hot_index": "2717213"
        },
        {
            "time": "2022-06-06 02:06:48.552259+08:00",
            "hot_index": "3145074"
        },
        {
            "time": "2022-06-06 03:01:51.128454+08:00",
            "hot_index": "3446013"
        },
        {
            "time": "2022-06-06 04:02:36.746071+08:00",
            "hot_index": "3460938"
        },
        {
            "time": "2022-06-06 05:04:11.365831+08:00",
            "hot_index": "3120708"
        },
        {
            "time": "2022-06-06 06:02:10.705190+08:00",
            "hot_index": "3048895"
        },
        {
            "time": "2022-06-06 07:02:22.039998+08:00",
            "hot_index": "3199347"
        },
        {
            "time": "2022-06-06 08:26:34.882912+08:00",
            "hot_index": "2056048"
        }
    ],
    "女游客登龙舟被网暴 龙舟协会回应": [
        {
            "time": "2022-06-06 00:05:45.407270+08:00",
            "hot_index": "2242696"
        },
        {
            "time": "2022-06-06 01:03:07.382417+08:00",
            "hot_index": "3272065"
        },
        {
            "time": "2022-06-06 02:06:48.552259+08:00",
            "hot_index": "4099919"
        },
        {
            "time": "2022-06-06 03:01:51.128454+08:00",
            "hot_index": "3064212"
        },
        {
            "time": "2022-06-06 04:02:36.746071+08:00",
            "hot_index": "2809270"
        },
        {
            "time": "2022-06-06 05:04:11.365831+08:00",
            "hot_index": "2683045"
        },
        {
            "time": "2022-06-06 06:02:10.705190+08:00",
            "hot_index": "3942426"
        },
        {
            "time": "2022-06-06 07:02:22.039998+08:00",
            "hot_index": "3795518"
        },
        {
            "time": "2022-06-06 08:26:34.882912+08:00",
            "hot_index": "3371703"
        }
    ],
    "刘洋发朋友圈：“准备，出发”": [
        {
            "time": "2022-06-06 00:05:45.407270+08:00",
            "hot_index": "2123750"
        },
        {
            "time": "2022-06-06 02:06:48.552259+08:00",
            "hot_index": "2273027"
        },
        {
            "time": "2022-06-06 03:01:51.128454+08:00",
            "hot_index": "2717662"
        },
        {
            "time": "2022-06-06 04:02:36.746071+08:00",
            "hot_index": "2033508"
        },
        {
            "time": "2022-06-06 05:04:11.365831+08:00",
            "hot_index": "2233209"
        },
        {
            "time": "2022-06-06 06:02:10.705190+08:00",
            "hot_index": "2166588"
        },
        {
            "time": "2022-06-06 07:02:22.039998+08:00",
            "hot_index": "2331931"
        }
    ],
    "拨打120表述不清怎么办？专家解读": [
        {
            "time": "2022-06-06 00:05:45.407270+08:00",
            "hot_index": "2044671"
        },
        {
            "time": "2022-06-06 02:06:48.552259+08:00",
            "hot_index": "2161441"
        },
        {
            "time": "2022-06-06 03:01:51.128454+08:00",
            "hot_index": "2374487"
        },
        {
            "time": "2022-06-06 04:02:36.746071+08:00",
            "hot_index": "2285709"
        },
        {
            "time": "2022-06-06 06:02:10.705190+08:00",
            "hot_index": "2015253"
        },
        {
            "time": "2022-06-06 07:02:22.039998+08:00",
            "hot_index": "2434020"
        }
    ],
    "实拍菲律宾布卢桑火山喷发": [
        {
            "time": "2022-06-06 01:03:07.382417+08:00",
            "hot_index": "4595571"
        },
        {
            "time": "2022-06-06 07:02:22.039998+08:00",
            "hot_index": "2562447"
        }
    ],
    "官方：高校学生返乡确需隔离的免费": [
        {
            "time": "2022-06-06 01:03:07.382417+08:00",
            "hot_index": "4278012"
        },
        {
            "time": "2022-06-06 06:02:10.705190+08:00",
            "hot_index": "2640061"
        },
        {
            "time": "2022-06-06 07:02:22.039998+08:00",
            "hot_index": "2059665"
        }
    ],
    "纳达尔夺法网第14冠 大满贯第22冠": [
        {
            "time": "2022-06-06 01:03:07.382417+08:00",
            "hot_index": "3541415"
        },
        {
            "time": "2022-06-06 02:06:48.552259+08:00",
            "hot_index": "3597915"
        },
        {
            "time": "2022-06-06 03:01:51.128454+08:00",
            "hot_index": "3504759"
        },
        {
            "time": "2022-06-06 04:02:36.746071+08:00",
            "hot_index": "3568864"
        },
        {
            "time": "2022-06-06 05:04:11.365831+08:00",
            "hot_index": "3582023"
        },
        {
            "time": "2022-06-06 06:02:10.705190+08:00",
            "hot_index": "3571937"
        },
        {
            "time": "2022-06-06 07:02:22.039998+08:00",
            "hot_index": "3560964"
        },
        {
            "time": "2022-06-06 08:26:34.882912+08:00",
            "hot_index": "3573145"
        }
    ],
    "澳炒作被中国战机干扰 专家解读": [
        {
            "time": "2022-06-06 01:03:07.382417+08:00",
            "hot_index": "3479477"
        },
        {
            "time": "2022-06-06 05:04:11.365831+08:00",
            "hot_index": "2479057"
        }
    ],
    "韩国：朝鲜发射8枚短程弹道导弹": [
        {
            "time": "2022-06-06 01:03:07.382417+08:00",
            "hot_index": "2464423"
        },
        {
            "time": "2022-06-06 06:02:10.705190+08:00",
            "hot_index": "2471577"
        },
        {
            "time": "2022-06-06 08:26:34.882912+08:00",
            "hot_index": "2841747"
        }
    ],
    "日乒协规定赢中国前三单独加分": [
        {
            "time": "2022-06-06 02:06:48.552259+08:00",
            "hot_index": "3874119"
        },
        {
            "time": "2022-06-06 03:01:51.128454+08:00",
            "hot_index": "2083999"
        }
    ],
    "伤者回忆列车脱轨：车头一度横着走": [
        {
            "time": "2022-06-06 02:06:48.552259+08:00",
            "hot_index": "2625617"
        }
    ],
    "100秒看神十四从发射到对接": [
        {
            "time": "2022-06-06 02:06:48.552259+08:00",
            "hot_index": "2371902"
        }
    ],
    "乌媒：乌克兰全境拉响防空警报": [
        {
            "time": "2022-06-06 02:06:48.552259+08:00",
            "hot_index": "2033907"
        },
        {
            "time": "2022-06-06 03:01:51.128454+08:00",
            "hot_index": "2845908"
        },
        {
            "time": "2022-06-06 04:02:36.746071+08:00",
            "hot_index": "2142948"
        },
        {
            "time": "2022-06-06 05:04:11.365831+08:00",
            "hot_index": "2023405"
        }
    ],
    "刘洋进舱三连拍：挥手、敬礼、比心": [
        {
            "time": "2022-06-06 03:01:51.128454+08:00",
            "hot_index": "2128962"
        }
    ],
    "现场：韩美举行海上联合军事演习": [
        {
            "time": "2022-06-06 04:02:36.746071+08:00",
            "hot_index": "3845185"
        }
    ],
    "武大靖送神十四航天员出征": [
        {
            "time": "2022-06-06 04:02:36.746071+08:00",
            "hot_index": "2522834"
        }
    ],
    "从天和核心舱看神十四绝美画面": [
        {
            "time": "2022-06-06 04:02:36.746071+08:00",
            "hot_index": "2446392"
        }
    ],
    "乌克兰基辅市区内两区发生爆炸": [
        {
            "time": "2022-06-06 05:04:11.365831+08:00",
            "hot_index": "2801861"
        }
    ],
    "全国高考天气地图出炉": [
        {
            "time": "2022-06-06 06:02:10.705190+08:00",
            "hot_index": "3734231"
        }
    ],
    "上海新增社会面“2+1”": [
        {
            "time": "2022-06-06 06:02:10.705190+08:00",
            "hot_index": "2251310"
        },
        {
            "time": "2022-06-06 07:02:22.039998+08:00",
            "hot_index": "2148260"
        }
    ],
    "中国军机“干扰”加军机报道不实": [
        {
            "time": "2022-06-06 07:02:22.039998+08:00",
            "hot_index": "2235461"
        }
    ],
    "上海昨日新增本土4+4": [
        {
            "time": "2022-06-06 08:26:34.882912+08:00",
            "hot_index": "4999176"
        }
    ],
    "明天全国高考": [
        {
            "time": "2022-06-06 08:26:34.882912+08:00",
            "hot_index": "4808478"
        }
    ],
    "高考“钉子户”梁实第26次备考": [
        {
            "time": "2022-06-06 08:26:34.882912+08:00",
            "hot_index": "4687075"
        }
    ],
    "北京堂食重启": [
        {
            "time": "2022-06-06 08:26:34.882912+08:00",
            "hot_index": "4569799"
        }
    ],
    "梅西五子登科": [
        {
            "time": "2022-06-06 08:26:34.882912+08:00",
            "hot_index": "4256576"
        }
    ],
    "今日芒种": [
        {
            "time": "2022-06-06 08:26:34.882912+08:00",
            "hot_index": "4032159"
        }
    ],
    "首次上太空的蔡旭哲空中玩起了笔": [
        {
            "time": "2022-06-06 08:26:34.882912+08:00",
            "hot_index": "2597005"
        }
    ],
    "英国女王拄拐杖现身庆典最后一天": [
        {
            "time": "2022-06-06 08:26:34.882912+08:00",
            "hot_index": "2466582"
        }
    ]
}