{
    "10人当选全国脱贫攻坚楷模": [
        {
            "time": "2021-02-26 00:06:33.175623+08:00",
            "count": "4828673"
        },
        {
            "time": "2021-02-26 01:24:15.740684+08:00",
            "count": "4801007"
        },
        {
            "time": "2021-02-26 02:05:43.402505+08:00",
            "count": "4801674"
        },
        {
            "time": "2021-02-26 03:00:59.908800+08:00",
            "count": "4829891"
        },
        {
            "time": "2021-02-26 04:01:36.006509+08:00",
            "count": "4799936"
        }
    ],
    "姚策养母称偷换孩子明显是人为": [
        {
            "time": "2021-02-26 00:06:33.175623+08:00",
            "count": "4659670"
        },
        {
            "time": "2021-02-26 01:24:15.740684+08:00",
            "count": "4632971"
        },
        {
            "time": "2021-02-26 02:05:43.402505+08:00",
            "count": "4633615"
        },
        {
            "time": "2021-02-26 03:00:59.908800+08:00",
            "count": "4660844"
        },
        {
            "time": "2021-02-26 04:01:36.006509+08:00",
            "count": "4631938"
        }
    ],
    "带货女士内衣文案翻车 李诞道歉": [
        {
            "time": "2021-02-26 00:06:33.175623+08:00",
            "count": "4496581"
        },
        {
            "time": "2021-02-26 01:24:15.740684+08:00",
            "count": "4470817"
        },
        {
            "time": "2021-02-26 02:05:43.402505+08:00",
            "count": "4471439"
        },
        {
            "time": "2021-02-26 03:00:59.908800+08:00",
            "count": "4497715"
        },
        {
            "time": "2021-02-26 04:01:36.006509+08:00",
            "count": "4469820"
        }
    ],
    "求分配女友男生被7个女生加微信": [
        {
            "time": "2021-02-26 00:06:33.175623+08:00",
            "count": "4339201"
        },
        {
            "time": "2021-02-26 01:24:15.740684+08:00",
            "count": "4314339"
        },
        {
            "time": "2021-02-26 02:05:43.402505+08:00",
            "count": "4314938"
        },
        {
            "time": "2021-02-26 03:00:59.908800+08:00",
            "count": "4340295"
        },
        {
            "time": "2021-02-26 04:01:36.006509+08:00",
            "count": "4313376"
        }
    ],
    "中国代表当面警告英国德国": [
        {
            "time": "2021-02-26 00:06:33.175623+08:00",
            "count": "4187329"
        },
        {
            "time": "2021-02-26 01:24:15.740684+08:00",
            "count": "4163337"
        },
        {
            "time": "2021-02-26 02:05:43.402505+08:00",
            "count": "4163915"
        },
        {
            "time": "2021-02-26 03:00:59.908800+08:00",
            "count": "4188384"
        },
        {
            "time": "2021-02-26 04:01:36.006509+08:00",
            "count": "4162408"
        }
    ],
    "原德云社演员涉嫌诈骗罪将受审": [
        {
            "time": "2021-02-26 00:06:33.175623+08:00",
            "count": "4040772"
        },
        {
            "time": "2021-02-26 01:24:15.740684+08:00",
            "count": "4017620"
        },
        {
            "time": "2021-02-26 02:05:43.402505+08:00",
            "count": "4018178"
        },
        {
            "time": "2021-02-26 03:00:59.908800+08:00",
            "count": "4041791"
        },
        {
            "time": "2021-02-26 04:01:36.006509+08:00",
            "count": "4016724"
        }
    ],
    "元宵赏灯赏月指数地图": [
        {
            "time": "2021-02-26 00:06:33.175623+08:00",
            "count": "3899345"
        },
        {
            "time": "2021-02-26 01:24:15.740684+08:00",
            "count": "3877003"
        },
        {
            "time": "2021-02-26 02:05:43.402505+08:00",
            "count": "3877542"
        },
        {
            "time": "2021-02-26 03:00:59.908800+08:00",
            "count": "3900328"
        },
        {
            "time": "2021-02-26 04:01:36.006509+08:00",
            "count": "3876139"
        }
    ],
    "35美元买的青花瓷碗估价50万美元": [
        {
            "time": "2021-02-26 00:06:33.175623+08:00",
            "count": "3762868"
        },
        {
            "time": "2021-02-26 01:24:15.740684+08:00",
            "count": "3741308"
        },
        {
            "time": "2021-02-26 02:05:43.402505+08:00",
            "count": "3741828"
        },
        {
            "time": "2021-02-26 03:00:59.908800+08:00",
            "count": "3763817"
        },
        {
            "time": "2021-02-26 04:01:36.006509+08:00",
            "count": "3740474"
        }
    ],
    "企业表彰员工在中印冲突中配合侦察": [
        {
            "time": "2021-02-26 00:06:33.175623+08:00",
            "count": "3631168"
        },
        {
            "time": "2021-02-26 01:24:15.740684+08:00",
            "count": "3610362"
        },
        {
            "time": "2021-02-26 02:05:43.402505+08:00",
            "count": "3610864"
        },
        {
            "time": "2021-02-26 03:00:59.908800+08:00",
            "count": "3632083"
        },
        {
            "time": "2021-02-26 04:01:36.006509+08:00",
            "count": "3609557"
        }
    ],
    "库克获8亿元年终奖": [
        {
            "time": "2021-02-26 00:06:33.175623+08:00",
            "count": "3504077"
        },
        {
            "time": "2021-02-26 01:24:15.740684+08:00",
            "count": "3484000"
        },
        {
            "time": "2021-02-26 02:05:43.402505+08:00",
            "count": "3484484"
        },
        {
            "time": "2021-02-26 03:00:59.908800+08:00",
            "count": "3504960"
        },
        {
            "time": "2021-02-26 04:01:36.006509+08:00",
            "count": "3483223"
        }
    ],
    "“西部歌王”高保利因车祸去世": [
        {
            "time": "2021-02-26 00:06:33.175623+08:00",
            "count": "3381434"
        },
        {
            "time": "2021-02-26 01:24:15.740684+08:00",
            "count": "3362060"
        },
        {
            "time": "2021-02-26 02:05:43.402505+08:00",
            "count": "3362527"
        },
        {
            "time": "2021-02-26 03:00:59.908800+08:00",
            "count": "3382287"
        },
        {
            "time": "2021-02-26 04:01:36.006509+08:00",
            "count": "3361310"
        }
    ],
    "杨天真说工作要有渣男心态": [
        {
            "time": "2021-02-26 00:06:33.175623+08:00",
            "count": "3263084"
        },
        {
            "time": "2021-02-26 01:24:15.740684+08:00",
            "count": "3244388"
        },
        {
            "time": "2021-02-26 02:05:43.402505+08:00",
            "count": "3244838"
        },
        {
            "time": "2021-02-26 03:00:59.908800+08:00",
            "count": "3263907"
        },
        {
            "time": "2021-02-26 04:01:36.006509+08:00",
            "count": "3243664"
        }
    ],
    "台当局驳回向华强居留台湾申请": [
        {
            "time": "2021-02-26 00:06:33.175623+08:00",
            "count": "3148876"
        },
        {
            "time": "2021-02-26 01:24:15.740684+08:00",
            "count": "3130834"
        },
        {
            "time": "2021-02-26 02:05:43.402505+08:00",
            "count": "3131269"
        },
        {
            "time": "2021-02-26 03:00:59.908800+08:00",
            "count": "3149670"
        },
        {
            "time": "2021-02-26 04:01:36.006509+08:00",
            "count": "3130136"
        }
    ],
    "韩国约2成网吧关门挖比特币": [
        {
            "time": "2021-02-26 00:06:33.175623+08:00",
            "count": "3038665"
        },
        {
            "time": "2021-02-26 01:24:15.740684+08:00",
            "count": "3021255"
        },
        {
            "time": "2021-02-26 02:05:43.402505+08:00",
            "count": "3021675"
        },
        {
            "time": "2021-02-26 03:00:59.908800+08:00",
            "count": "3039431"
        },
        {
            "time": "2021-02-26 04:01:36.006509+08:00",
            "count": "3020581"
        }
    ],
    "邮件快件包装管理办法发布": [
        {
            "time": "2021-02-26 00:06:33.175623+08:00",
            "count": "2932312"
        },
        {
            "time": "2021-02-26 01:24:15.740684+08:00",
            "count": "2915511"
        },
        {
            "time": "2021-02-26 02:05:43.402505+08:00",
            "count": "2915916"
        },
        {
            "time": "2021-02-26 03:00:59.908800+08:00",
            "count": "2933051"
        },
        {
            "time": "2021-02-26 04:01:36.006509+08:00",
            "count": "2914861"
        }
    ],
    "国家乡村振兴局正式挂牌": [
        {
            "time": "2021-02-26 00:06:33.175623+08:00",
            "count": "2829681"
        },
        {
            "time": "2021-02-26 01:24:15.740684+08:00",
            "count": "2813468"
        },
        {
            "time": "2021-02-26 02:05:43.402505+08:00",
            "count": "2813859"
        },
        {
            "time": "2021-02-26 03:00:59.908800+08:00",
            "count": "2830394"
        },
        {
            "time": "2021-02-26 04:01:36.006509+08:00",
            "count": "2812840"
        }
    ],
    "纽约州长身陷性骚扰丑闻": [
        {
            "time": "2021-02-26 00:06:33.175623+08:00",
            "count": "2730642"
        },
        {
            "time": "2021-02-26 01:24:15.740684+08:00",
            "count": "2714997"
        },
        {
            "time": "2021-02-26 02:05:43.402505+08:00",
            "count": "2715374"
        },
        {
            "time": "2021-02-26 03:00:59.908800+08:00",
            "count": "2731331"
        },
        {
            "time": "2021-02-26 04:01:36.006509+08:00",
            "count": "2714391"
        }
    ],
    "唐山急寻确诊病例密接者同乘人员": [
        {
            "time": "2021-02-26 00:06:33.175623+08:00",
            "count": "2635070"
        },
        {
            "time": "2021-02-26 01:24:15.740684+08:00",
            "count": "2619972"
        },
        {
            "time": "2021-02-26 02:05:43.402505+08:00",
            "count": "2620336"
        },
        {
            "time": "2021-02-26 03:00:59.908800+08:00",
            "count": "2635734"
        },
        {
            "time": "2021-02-26 04:01:36.006509+08:00",
            "count": "2619387"
        }
    ],
    "东京奥运会火炬传递3月开始": [
        {
            "time": "2021-02-26 00:06:33.175623+08:00",
            "count": "2542842"
        },
        {
            "time": "2021-02-26 01:24:15.740684+08:00",
            "count": "2528273"
        },
        {
            "time": "2021-02-26 02:05:43.402505+08:00",
            "count": "2528624"
        },
        {
            "time": "2021-02-26 03:00:59.908800+08:00",
            "count": "2543483"
        },
        {
            "time": "2021-02-26 04:01:36.006509+08:00",
            "count": "2527709"
        }
    ],
    "香港计划8月1日起上调股票印花税": [
        {
            "time": "2021-02-26 00:06:33.175623+08:00",
            "count": "2453843"
        },
        {
            "time": "2021-02-26 01:24:15.740684+08:00",
            "count": "2271987"
        },
        {
            "time": "2021-02-26 02:05:43.402505+08:00",
            "count": "2272303"
        },
        {
            "time": "2021-02-26 03:00:59.908800+08:00",
            "count": "2368555"
        },
        {
            "time": "2021-02-26 04:01:36.006509+08:00",
            "count": "2271480"
        }
    ],
    "春节后机票价格大跳水": [
        {
            "time": "2021-02-26 00:06:33.175623+08:00",
            "count": "2367958"
        },
        {
            "time": "2021-02-26 01:24:15.740684+08:00",
            "count": "2192467"
        },
        {
            "time": "2021-02-26 02:05:43.402505+08:00",
            "count": "2192772"
        },
        {
            "time": "2021-02-26 03:00:59.908800+08:00",
            "count": "2205658"
        },
        {
            "time": "2021-02-26 04:01:36.006509+08:00",
            "count": "2191978"
        }
    ],
    "山西超市顶棚被暴雪压塌4人受伤": [
        {
            "time": "2021-02-26 00:06:33.175623+08:00",
            "count": "2285080"
        }
    ],
    "趵突泉将6万余元硬币上交财政": [
        {
            "time": "2021-02-26 00:06:33.175623+08:00",
            "count": "2205102"
        },
        {
            "time": "2021-02-26 01:24:15.740684+08:00",
            "count": "2439783"
        },
        {
            "time": "2021-02-26 02:05:43.402505+08:00",
            "count": "2440122"
        },
        {
            "time": "2021-02-26 03:00:59.908800+08:00",
            "count": "2454461"
        },
        {
            "time": "2021-02-26 04:01:36.006509+08:00",
            "count": "2439239"
        }
    ],
    "广州拾金不昧可获10%奖励": [
        {
            "time": "2021-02-26 00:06:33.175623+08:00",
            "count": "2127923"
        },
        {
            "time": "2021-02-26 01:24:15.740684+08:00",
            "count": "2354391"
        },
        {
            "time": "2021-02-26 02:05:43.402505+08:00",
            "count": "2354718"
        },
        {
            "time": "2021-02-26 03:00:59.908800+08:00",
            "count": "2285656"
        },
        {
            "time": "2021-02-26 04:01:36.006509+08:00",
            "count": "2353866"
        }
    ],
    "多地控制中小学考试次数和作业量": [
        {
            "time": "2021-02-26 00:06:33.175623+08:00",
            "count": "2053446"
        },
        {
            "time": "2021-02-26 01:24:15.740684+08:00",
            "count": "2041680"
        },
        {
            "time": "2021-02-26 02:05:43.402505+08:00",
            "count": "2041964"
        },
        {
            "time": "2021-02-26 03:00:59.908800+08:00",
            "count": "2053964"
        },
        {
            "time": "2021-02-26 04:01:36.006509+08:00",
            "count": "2041225"
        }
    ],
    "患多种疾病张桂梅说怕睡一觉人没了": [
        {
            "time": "2021-02-26 00:06:33.175623+08:00",
            "count": "1981575"
        },
        {
            "time": "2021-02-26 01:24:15.740684+08:00",
            "count": "1970222"
        },
        {
            "time": "2021-02-26 02:05:43.402505+08:00",
            "count": "1970495"
        },
        {
            "time": "2021-02-26 03:00:59.908800+08:00",
            "count": "1982075"
        },
        {
            "time": "2021-02-26 04:01:36.006509+08:00",
            "count": "1900840"
        }
    ],
    "波士顿动力机器狗上岗纽约警局": [
        {
            "time": "2021-02-26 00:06:33.175623+08:00",
            "count": "1912220"
        },
        {
            "time": "2021-02-26 01:24:15.740684+08:00",
            "count": "1901264"
        },
        {
            "time": "2021-02-26 02:05:43.402505+08:00",
            "count": "1901528"
        },
        {
            "time": "2021-02-26 03:00:59.908800+08:00",
            "count": "1912702"
        },
        {
            "time": "2021-02-26 04:01:36.006509+08:00",
            "count": "1969782"
        }
    ],
    "涉事货拉拉司机开过饭店有房有车": [
        {
            "time": "2021-02-26 00:06:33.175623+08:00",
            "count": "1845292"
        },
        {
            "time": "2021-02-26 01:24:15.740684+08:00",
            "count": "1834720"
        },
        {
            "time": "2021-02-26 02:05:43.402505+08:00",
            "count": "1834974"
        },
        {
            "time": "2021-02-26 03:00:59.908800+08:00",
            "count": "1845758"
        },
        {
            "time": "2021-02-26 04:01:36.006509+08:00",
            "count": "1834310"
        }
    ],
    "一家12口持BNO护照投奔英国被遣返": [
        {
            "time": "2021-02-26 00:06:33.175623+08:00",
            "count": "1780707"
        },
        {
            "time": "2021-02-26 01:24:15.740684+08:00",
            "count": "1770504"
        },
        {
            "time": "2021-02-26 02:05:43.402505+08:00",
            "count": "1770750"
        },
        {
            "time": "2021-02-26 03:00:59.908800+08:00",
            "count": "1781156"
        },
        {
            "time": "2021-02-26 04:01:36.006509+08:00",
            "count": "1770109"
        }
    ],
    "上海发现低龄自闭症患儿新药": [
        {
            "time": "2021-02-26 00:06:33.175623+08:00",
            "count": "1718382"
        },
        {
            "time": "2021-02-26 01:24:15.740684+08:00",
            "count": "1708537"
        },
        {
            "time": "2021-02-26 02:05:43.402505+08:00",
            "count": "1708774"
        },
        {
            "time": "2021-02-26 03:00:59.908800+08:00",
            "count": "1718816"
        },
        {
            "time": "2021-02-26 04:01:36.006509+08:00",
            "count": "1708156"
        }
    ],
    "女子用行李箱阻挡高铁车门被拘": [
        {
            "time": "2021-02-26 01:24:15.740684+08:00",
            "count": "2115731"
        },
        {
            "time": "2021-02-26 02:05:43.402505+08:00",
            "count": "2116025"
        },
        {
            "time": "2021-02-26 03:00:59.908800+08:00",
            "count": "2128460"
        },
        {
            "time": "2021-02-26 04:01:36.006509+08:00",
            "count": "2115259"
        }
    ]
}